git_clean/__init__.py
git_clean/cleaner.py
git_clean/cli.py
git_clean/exc.py
git_clean-0.1.0b1.dist-info/entry_points.txt
git_clean-0.1.0b1.dist-info/WHEEL
git_clean-0.1.0b1.dist-info/METADATA
git_clean-0.1.0b1.dist-info/RECORD
